Data/__init__.py
Data/params/__init__.py
feature_selection_methods/__init__.py
feature_selection_methods/feature_selection.py
feature_selection_methods/normalizmethods.py
immune_score/__init__.py
immune_score/calculate.py
immune_score/gsea_func.py
immune_score/interprate_func.py
immune_score/manhattan_dis.py
immune_score/score_caculator.py
Immune_Score_Project-0.0.2.dist-info/LICENSE
Immune_Score_Project-0.0.2.dist-info/METADATA
Immune_Score_Project-0.0.2.dist-info/WHEEL
Immune_Score_Project-0.0.2.dist-info/top_level.txt
Immune_Score_Project-0.0.2.dist-info/RECORD
