Metadata-Version: 2.1
Name: Immune-Score-Project
Version: 0.0.2
Summary: An useless project.
Home-page: https://github.com/Prophet2023/Immune-Score-Projcet
Author: Tan Zhenlin
Author-email: d202381031@hust.edu.cn
License: MIT
Keywords: immune,immunity
Classifier: Development Status :: 1 - Planning
Classifier: Intended Audience :: Science/Research
Classifier: Intended Audience :: Developers
Classifier: License :: OSI Approved :: MIT License
Classifier: Programming Language :: Python
Classifier: Programming Language :: Python :: 3
Classifier: Programming Language :: Python :: 3.6
Classifier: Programming Language :: Python :: 3.7
Classifier: Programming Language :: Python :: 3.8
Classifier: Programming Language :: Python :: 3.9
Classifier: Programming Language :: Python :: 3.10
Classifier: Programming Language :: Python :: 3 :: Only
Classifier: Topic :: Software Development
Classifier: Topic :: Scientific/Engineering
Classifier: Operating System :: Microsoft :: Windows
Classifier: Operating System :: POSIX :: Linux
Classifier: Operating System :: MacOS
Requires-Python: >=3.6
License-File: LICENSE
Requires-Dist: pandas (>0.20.0)
Requires-Dist: numpy (>1.0.0)
Requires-Dist: scikit-learn (>1.1.0)
Requires-Dist: scipy (>1.5.4)
